pydanfossair/__init__.py
pydanfossair/__main__.py
pydanfossair/commands.py
pydanfossair/danfossclient.py
pydanfossair/operation_mode.py
pydanfossair-0.3.0.dist-info/LICENSE
pydanfossair-0.3.0.dist-info/METADATA
pydanfossair-0.3.0.dist-info/WHEEL
pydanfossair-0.3.0.dist-info/top_level.txt
pydanfossair-0.3.0.dist-info/RECORD
