Metadata-Version: 2.1
Name: pydanfossair
Version: 0.3.0
Summary: Python interface for Danfoss Air HRV systems
Home-page: https://github.com/JonasPed/pydanfoss-air
Author: Jonas Pedersen
Author-email: jonas@pedersen.ninja
License: Apache 2.0
License-File: LICENSE
